LICENCE.txt
MANIFEST.in
README.md
setup.py
try.py
burclar/__init__.py
burclar.egg-info/PKG-INFO
burclar.egg-info/SOURCES.txt
burclar.egg-info/dependency_links.txt
burclar.egg-info/requires.txt
burclar.egg-info/top_level.txt