Metadata-Version: 2.1
Name: burclar
Version: 1.1.0
Summary: Basit bir burç modülü.
Home-page: https://github.com/The-Special/Burc-api
Author: Special
Author-email: 
License: MIT License
Keywords: burçlar,python,burc-api
Platform: UNKNOWN
Classifier: Development Status :: 5 - Production/Stable
Classifier: Intended Audience :: Developers
Classifier: Operating System :: Microsoft :: Windows :: Windows 10
Classifier: License :: OSI Approved :: MIT License
Classifier: Programming Language :: Python :: 3
